calculator_tsukrus/Dockerfile
calculator_tsukrus/__init__.py
calculator_tsukrus/calculator.py
calculator_tsukrus-2.1.dist-info/LICENSE
calculator_tsukrus-2.1.dist-info/WHEEL
calculator_tsukrus-2.1.dist-info/METADATA
calculator_tsukrus-2.1.dist-info/RECORD
