Metadata-Version: 2.1
Name: calculator_tsukrus
Version: 2.1
Summary: Calculator module
Author-email: Rokas Burneika <rokas.burneika@gmail.com>
Classifier: License :: OSI Approved :: MIT License
